raven_sh.py
raven_sh-0.5.1.dist-info/LICENSE
raven_sh-0.5.1.dist-info/METADATA
raven_sh-0.5.1.dist-info/WHEEL
raven_sh-0.5.1.dist-info/entry_points.txt
raven_sh-0.5.1.dist-info/top_level.txt
raven_sh-0.5.1.dist-info/RECORD
