Metadata-Version: 2.1
Name: raven-sh
Version: 0.5.1
Summary: raven-sh is a client for Sentry which can be used as a wrapper for cron jobs
Home-page: https://github.com/doist/raven-sh
Author: Doist Developers
Author-email: dev@doist.com
License: MIT
Platform: UNKNOWN
Classifier: License :: OSI Approved :: MIT License
Classifier: Intended Audience :: Developers
Classifier: Intended Audience :: System Administrators
Classifier: Topic :: Software Development
Classifier: Programming Language :: Python
Classifier: Programming Language :: Python :: 2
Classifier: Programming Language :: Python :: 2.7
Classifier: Programming Language :: Python :: 3
Classifier: Programming Language :: Python :: 3.7
Requires-Dist: sentry-sdk (>=0.7.10)
